builderknower/__init__.py
builderknower/module.py
builderknower-0.1.1.dist-info/LICENSE
builderknower-0.1.1.dist-info/METADATA
builderknower-0.1.1.dist-info/WHEEL
builderknower-0.1.1.dist-info/top_level.txt
builderknower-0.1.1.dist-info/RECORD
